blocksec2go/__init__.py
blocksec2go/__main__.py
blocksec2go/commands.py
blocksec2go/util.py
blocksec2go/cli/__init__.py
blocksec2go/cli/change_pin.py
blocksec2go/cli/disable_pin.py
blocksec2go/cli/encrypted_keyimport.py
blocksec2go/cli/generate_keypair.py
blocksec2go/cli/generate_signature.py
blocksec2go/cli/get_card_info.py
blocksec2go/cli/get_key_info.py
blocksec2go/cli/list_readers.py
blocksec2go/cli/main.py
blocksec2go/cli/set_pin.py
blocksec2go/cli/unlock_pin.py
blocksec2go/comm/__init__.py
blocksec2go/comm/base.py
blocksec2go/comm/card_observer.py
blocksec2go/comm/pyscard.py
blocksec2go-1.2.dist-info/LICENSE
blocksec2go-1.2.dist-info/METADATA
blocksec2go-1.2.dist-info/WHEEL
blocksec2go-1.2.dist-info/entry_points.txt
blocksec2go-1.2.dist-info/top_level.txt
blocksec2go-1.2.dist-info/RECORD
