Metadata-Version: 2.1
Name: blocksec2go
Version: 1.2
Summary: Allow for communication with Infineon's Blockchain Security 2Go starter kit
Home-page: https://github.com/Infineon/BlockchainSecurity2Go-Python-Library
Author: Infineon Technologies AG
Author-email: blockchain@infineon.com
License: MIT
Platform: UNKNOWN
Classifier: Programming Language :: Python :: 3
Classifier: Development Status :: 3 - Alpha
Classifier: Environment :: Console
Classifier: Intended Audience :: Developers
Classifier: Intended Audience :: Education
Classifier: Topic :: Software Development :: Libraries
Classifier: License :: OSI Approved :: MIT License
Classifier: Operating System :: OS Independent
Requires-Dist: pyscard
Requires-Dist: cryptography
